django_rest_aggregation/__init__.py
django_rest_aggregation/aggregator.py
django_rest_aggregation/enums.py
django_rest_aggregation/filter.py
django_rest_aggregation/mixins.py
django_rest_aggregation/serializers.py
django_rest_aggregation-0.4.0.dist-info/LICENSE
django_rest_aggregation-0.4.0.dist-info/METADATA
django_rest_aggregation-0.4.0.dist-info/WHEEL
django_rest_aggregation-0.4.0.dist-info/top_level.txt
django_rest_aggregation-0.4.0.dist-info/RECORD
