Metadata-Version: 2.1
Name: django_rest_aggregation
Version: 0.4.0
Summary: A DRF mixin for aggregation endpoints
Author-email: Simon Legtenborg <simon.legtenborg@singular-it.de>
Project-URL: Homepage, https://github.com/singularit-de/django-rest-aggregation/
Project-URL: Bug Tracker, https://github.com/singularit-de/django-rest-aggregation/issues
Classifier: Programming Language :: Python :: 3
Classifier: License :: OSI Approved :: MIT License
Classifier: Operating System :: OS Independent
Requires-Python: >=3.8
License-File: LICENSE
